icecube_skywriter-1.0.1.dist-info/licenses/LICENSE
skywriter/__init__.py
skywriter/i3_to_json.py
skywriter/logging_utils.py
skywriter/py.typed
icecube_skywriter-1.0.1.dist-info/METADATA
icecube_skywriter-1.0.1.dist-info/WHEEL
icecube_skywriter-1.0.1.dist-info/top_level.txt
icecube_skywriter-1.0.1.dist-info/RECORD
