Metadata-Version: 2.4
Name: icecube-skywriter
Version: 1.0.1
Summary: Upstream Tools for SkyDriver & the Skymap Scanner
Author-email: WIPAC Developers <developers@icecube.wisc.edu>
License-Expression: MIT
Project-URL: Homepage, https://pypi.org/project/icecube-skywriter/
Project-URL: Tracker, https://github.com/icecube/skywriter/issues
Project-URL: Source, https://github.com/icecube/skywriter
Keywords: IceCube,skymap scanner,skymap,HEALPix,neutrino,reconstruction
Classifier: Programming Language :: Python :: 3.10
Classifier: Programming Language :: Python :: 3.11
Classifier: Programming Language :: Python :: 3.12
Classifier: Programming Language :: Python :: 3.13
Classifier: Programming Language :: Python :: 3.14
Requires-Python: <3.15,>=3.10
License-File: LICENSE
Requires-Dist: wipac-dev-tools
Provides-Extra: tests
Requires-Dist: pytest; extra == "tests"
Requires-Dist: pytest-mock; extra == "tests"
Provides-Extra: mypy
Requires-Dist: pytest; extra == "mypy"
Requires-Dist: pytest-mock; extra == "mypy"
Dynamic: license-file
